hdrlocal/__init__.py
hdrlocal/clahe.py
hdrlocal/processor.py
hdrlocal/util.py
hdr_local_processing-0.1.4.dist-info/METADATA
hdr_local_processing-0.1.4.dist-info/WHEEL
hdr_local_processing-0.1.4.dist-info/top_level.txt
hdr_local_processing-0.1.4.dist-info/RECORD
