Metadata-Version: 2.1
Name: hdr-local-processing
Version: 0.1.4
Summary: Petri Local Tonemapping Package
Home-page: https://github.com/Elessar11777
Author: Elessar11777
Author-email: Elessar11777@gmail.com
License: GPL
Platform: UNKNOWN
Requires-Dist: numpy
Requires-Dist: opencv-python
